{
  "image": "mcr.microsoft.com/devcontainers/base:ubuntu",
  "features": {
    "ghcr.io/rocker-org/devcontainer-features/apt-packages:1": {
      "packages": "pkg-config"
    },
    "ghcr.io/devcontainers-contrib/features/haskell:2": {
      "globalPackages": "hlint ormolu"
    }
  },
  "customizations": {
    "vscode": {
      "extensions": [
        "haskell.haskell"
      ],
      "settings": {
        "editor.formatOnSave": true,
        "git.fetchOnPull": true,
        "git.autofetch": true,
        "git.pruneOnFetch": true,
        "git.autofetchPeriod": 3600,
        "githubPullRequests.ignoredPullRequestBranches": [
          "main"
        ]
      }
    }
  },
  "onCreateCommand": {
    "clean": "cp ~/.cabal/bin/* ~/.local/bin/ && rm -r ~/.cabal/",
    "stack": "stack build --test --no-run-tests --haddock --no-haddock-deps --haddock-arguments=--no-warnings"
  },
  "hostRequirements": {
    "memory": "8gb",
    "storage": "32gb"
  }
}
